lbp_print/__about__.py
lbp_print/__init__.py
lbp_print/cli.py
lbp_print/config.py
lbp_print/core.py
lbp_print/src/__init__.py
lbp_print/src/lbppy/__init__.py
lbp_print/src/lbppy/setup.py
lbp_print/src/lbppy/test.py
lbp_print/src/lbppy/lbppy/__init__.py
lbp_print/src/lbppy/lbppy/expression.py
lbp_print/src/lbppy/lbppy/file.py
lbp_print/src/lbppy/lbppy/file_part.py
lbp_print/src/lbppy/lbppy/manifestation.py
lbp_print/src/lbppy/lbppy/query.py
lbp_print/src/lbppy/lbppy/resource.py
lbp_print/src/lbppy/lbppy/resource_identifier.py
lbp_print/src/lbppy/lbppy/transcription.py
lbp_print/test/__init__.py
lbp_print/test/test_cli.py
lbp_print/test/test_remote.py
lbp_print/test/test_tex.py
lbp_print/vendor/saxon9he.jar
lbp_print/xslt/.git
lbp_print/xslt/Changelog.md
lbp_print/xslt/LICENSE
lbp_print/xslt/README.md
lbp_print/xslt/0.0.0/critical.xslt
lbp_print/xslt/0.0.0/diplomatic.xslt
lbp_print/xslt/1.0.0/critical.xslt
lbp_print/xslt/1.0.0/diplomatic.xslt
lbp_print/xslt/1.0.0/localisation.xml
lbp_print/xslt/1.0.0/modules/critical/apparatus.xsl
lbp_print/xslt/1.0.0/modules/critical/block-elements.xsl
lbp_print/xslt/1.0.0/modules/critical/inline-elements.xsl
lbp_print/xslt/1.0.0/modules/critical/preamble.xsl
lbp_print/xslt/1.0.0/modules/critical/references.xsl
lbp_print/xslt/1.0.0/modules/critical/translation.xsl
lbp_print/xslt/default/critical.xslt
lbp_print/xslt/default/diplomatic.xslt
lbp_print-0.1.3.dist-info/METADATA
lbp_print-0.1.3.dist-info/WHEEL
lbp_print-0.1.3.dist-info/dependency_links.txt
lbp_print-0.1.3.dist-info/entry_points.txt
lbp_print-0.1.3.dist-info/top_level.txt
lbp_print-0.1.3.dist-info/RECORD
